MEGA/__init__.py
MEGA/_version.py
MEGA/cli.py
MEGA/log.py
MEGA/data/NJS16_metabolic_relation.txt
MEGA/data/cre_abundance_data.csv
MEGA/data/cre_metadata.csv
MEGA/lib/__init__.py
MEGA/pyHGT/__init__.py
MEGA/pyHGT/conv.py
MEGA/pyHGT/data.py
MEGA/pyHGT/model.py
MEGA/pyHGT/utils.py
MEGA/r_scripts/taxize.r
pyMEGA-0.0.5.dist-info/LICENSE
pyMEGA-0.0.5.dist-info/METADATA
pyMEGA-0.0.5.dist-info/WHEEL
pyMEGA-0.0.5.dist-info/entry_points.txt
pyMEGA-0.0.5.dist-info/top_level.txt
pyMEGA-0.0.5.dist-info/RECORD
