Metadata-Version: 2.1
Name: pyMEGA
Version: 0.0.5
Summary: MEGA is a deep learning package for identifying cancer-associated tissue-resident microbes
Home-page: https://github.com/OSU-BMBL/MEGA
Author: Cankun Wang
Author-email: cankun.wang@osumc.edu
License: MIT
Classifier: Programming Language :: Python :: 3.7
Classifier: License :: OSI Approved :: MIT License
Classifier: Operating System :: OS Independent
Requires-Python: >=3.7
License-File: LICENSE
